sodius/__init__.py
sodius/cli_wrapper.py
copiex-0.1.0.dist-info/METADATA
copiex-0.1.0.dist-info/WHEEL
copiex-0.1.0.dist-info/entry_points.txt
copiex-0.1.0.dist-info/top_level.txt
copiex-0.1.0.dist-info/RECORD
